realtpl/ZeroDict.py
realtpl/__init__.py
realtpl/calc_all.py
realtpl/calc_compressibility.py
realtpl/calc_cp_ref_nasa.py
realtpl/calc_cv_cp_sound.py
realtpl/calc_visc_cond_chung.py
realtpl/config.py
realtpl/data_association_parameter.py
realtpl/data_dipole_moment.py
realtpl/eos_data.py
realtpl/fluid_properties.py
realtpl/nasa.py
realtpl/nasa_7.yaml
realtpl/nasa_9.yaml
realtpl/ref_data_from_coolprop.py
realtpl/thermophysical_constants.py
realtpl/visualization.py
realtpl/write_data_to_files.py
realtpl-0.0.9.dist-info/LICENSE
realtpl-0.0.9.dist-info/METADATA
realtpl-0.0.9.dist-info/WHEEL
realtpl-0.0.9.dist-info/entry_points.txt
realtpl-0.0.9.dist-info/top_level.txt
realtpl-0.0.9.dist-info/RECORD
