Metadata-Version: 2.1
Name: realtpl
Version: 0.0.9
Summary: Computation of real gas thermodynamics for fluids at different pressures and temperatures.
Home-page: https://github.com/ttrummler/realtpl
Author: T Trummler, M Glatzle
Author-email: theresa.trummler@gmail.com
License: GNU General Public License v3 or later (GPLv3+)
Keywords: thermodynamics,cubic equation of state
Classifier: License :: OSI Approved :: GNU General Public License v3 or later (GPLv3+)
Classifier: Development Status :: 5 - Production/Stable
Classifier: Intended Audience :: Science/Research
Classifier: Programming Language :: Python
Classifier: Programming Language :: Python :: 3
Classifier: Programming Language :: Python :: 3.8
Classifier: Programming Language :: Python :: 3.9
Classifier: Programming Language :: Python :: 3.10
Classifier: Topic :: Scientific/Engineering
License-File: LICENSE
Requires-Dist: numpy
Requires-Dist: pandas
Requires-Dist: matplotlib
Requires-Dist: pyyaml
Requires-Dist: CoolProp
